README.rst
nodeon.py
setup.py
nodeon.egg-info/PKG-INFO
nodeon.egg-info/SOURCES.txt
nodeon.egg-info/dependency_links.txt
nodeon.egg-info/requires.txt
nodeon.egg-info/top_level.txt