Metadata-Version: 1.0
Name: nodeon
Version: 1.0.1
Summary: A program to create Node.js virtual environments.
Home-page: https://github.com/Shu-Ji/nodeon
Author: Finn
Author-email: UNKNOWN
License: UNKNOWN
Platform: UNKNOWN
